AVOlibrary2CP/__init__.py
AVOlibrary2CP/modulo.py
AVOlibrary2CP-0.4.dist-info/METADATA
AVOlibrary2CP-0.4.dist-info/WHEEL
AVOlibrary2CP-0.4.dist-info/top_level.txt
AVOlibrary2CP-0.4.dist-info/RECORD
